CHANGELOG.txt
LICENCE.txt
MANIFEST.in
README.txt
__init__.py
setup.py
sum.py
deploysample.egg-info/PKG-INFO
deploysample.egg-info/SOURCES.txt
deploysample.egg-info/dependency_links.txt
deploysample.egg-info/top_level.txt
mymodule.egg-info/SOURCES.txt
mymodule.egg-info/dependency_links.txt
mymodule.egg-info/top_level.txt