Metadata-Version: 2.1
Name: deploysample
Version: 0.0.1
Summary: adding numbers
Home-page: UNKNOWN
Author: Saurabh
Author-email: saurabhp@leewayhertz.com
License: MIT
Platform: UNKNOWN
License-File: LICENCE.txt
